{
  "+TEK - Stars and Bunnies/10922.qua": {
    "AudioFile": "audio.mp3",
    "SongPreviewTime": "63973",
    "BackgroundFile": "pixel art.jpg",
    "MapId": "10922",
    "MapSetId": "922",
    "Mode": "Keys7",
    "Title": "Stars and Bunnies",
    "Artist": "+TEK",
    "Source": "''",
    "Tags": "Quaver, edm, chiptune",
    "Creator": "yahweh",
    "DifficultyName": "Extra",
    "Description": "This is a Quaver converted version of yahweh's map.",
    "EditorLayers": "[]",
    "CustomAudioSamples": "[]",
    "SoundEffects": "[]",
    "BPM": 150,
    "SliderVelocities": "[]"
  },
  "+TEK - Stars and Bunnies/10923.qua": {
    "AudioFile": "audio.mp3",
    "SongPreviewTime": "63973",
    "BackgroundFile": "pixel art.jpg",
    "MapId": "10923",
    "MapSetId": "922",
    "Mode": "Keys7",
    "Title": "Stars and Bunnies",
    "Artist": "+TEK",
    "Source": "''",
    "Tags": "Quaver, edm, chiptune",
    "Creator": "yahweh",
    "DifficultyName": "Beginner",
    "Description": "Created at 1588007638000",
    "EditorLayers": "[]",
    "CustomAudioSamples": "[]",
    "SoundEffects": "[]",
    "BPM": 150,
    "SliderVelocities": "[]"
  },
  "+TEK - Stars and Bunnies/10924.qua": {
    "AudioFile": "audio.mp3",
    "SongPreviewTime": "63973",
    "BackgroundFile": "pixel art.jpg",
    "MapId": "10924",
    "MapSetId": "922",
    "Mode": "Keys7",
    "Title": "Stars and Bunnies",
    "Artist": "+TEK",
    "Source": "''",
    "Tags": "Quaver, edm, chiptune",
    "Creator": "yahweh",
    "DifficultyName": "Insane",
    "Description": "Created at 1588024622000",
    "EditorLayers": "[]",
    "CustomAudioSamples": "[]",
    "SoundEffects": "[]",
    "BPM": 150,
    "SliderVelocities": "[]"
  },
  "+TEK - Stars and Bunnies/10925.qua": {
    "AudioFile": "audio.mp3",
    "SongPreviewTime": "63973",
    "BackgroundFile": "pixel art.jpg",
    "MapId": "10925",
    "MapSetId": "922",
    "Mode": "Keys7",
    "Title": "Stars and Bunnies",
    "Artist": "+TEK",
    "Source": "''",
    "Tags": "Quaver, edm, chiptune",
    "Creator": "yahweh",
    "DifficultyName": "Easy",
    "Description": "Created at 1588083188000",
    "EditorLayers": "[]",
    "CustomAudioSamples": "[]",
    "SoundEffects": "[]",
    "BPM": 150,
    "SliderVelocities": "[]"
  },
  "+TEK - Stars and Bunnies/10926.qua": {
    "AudioFile": "audio.mp3",
    "SongPreviewTime": "63973",
    "BackgroundFile": "pixel art.jpg",
    "MapId": "10926",
    "MapSetId": "922",
    "Mode": "Keys7",
    "Title": "Stars and Bunnies",
    "Artist": "+TEK",
    "Source": "''",
    "Tags": "Quaver, edm, chiptune",
    "Creator": "yahweh",
    "DifficultyName": "Hard",
    "Description": "Created at 1588463302000",
    "EditorLayers": "[]",
    "CustomAudioSamples": "[]",
    "SoundEffects": "[]",
    "BPM": 150,
    "SliderVelocities": "[]"
  },
  "+TEK - Stars and Bunnies/10927.qua": {
    "AudioFile": "audio.mp3",
    "SongPreviewTime": "63973",
    "BackgroundFile": "pixel art.jpg",
    "MapId": "10927",
    "MapSetId": "922",
    "Mode": "Keys7",
    "Title": "Stars and Bunnies",
    "Artist": "+TEK",
    "Source": "''",
    "Tags": "Quaver, edm, chiptune",
    "Creator": "yahweh",
    "DifficultyName": "Normal",
    "Description": "Created at 1588711892000",
    "EditorLayers": "[]",
    "CustomAudioSamples": "[]",
    "SoundEffects": "[]",
    "BPM": 150,
    "SliderVelocities": "[]"
  },
  "11789 - 565/60414.qua": {
    "AudioFile": "audio.mp3",
    "BackgroundFile": "Rush b.jpg",
    "MapId": "60414",
    "MapSetId": "11789",
    "Mode": "Keys4",
    "Title": "RUSH B",
    "Artist": "Sheet Music Boss",
    "Source": "Youtube",
    "Tags": "''",
    "Creator": "Helowis123",
    "DifficultyName": "Russian Hard",
    "Description": "Created at 1632870701000",
    "EditorLayers": "[]",
    "CustomAudioSamples": "[]",
    "SoundEffects": "[]",
    "BPM": 500,
    "SliderVelocities": "[]"
  },
  "20075 - 750/91684.qua": {
    "AudioFile": "audio.mp3",
    "SongPreviewTime": "14970",
    "BackgroundFile": "memory lane bg better better.png",
    "MapId": "91684",
    "MapSetId": "20075",
    "Mode": "Keys4",
    "Title": "Memory Lane",
    "Artist": "AcesToAces",
    "Source": "''",
    "Tags": "yasuha, flyday chinatown, future funk, groove, sv",
    "Creator": "svKona",
    "DifficultyName": "Flyday Chinatown",
    "Description": "Created at 1658249465000",
    "EditorLayers": "[]",
    "CustomAudioSamples": "[]",
    "SoundEffects": "[]",
    "BPM": 128,
    "SliderVelocities": ""
  },
  "20075 - 750/91685.qua": {
    "AudioFile": "audio.mp3",
    "SongPreviewTime": "14970",
    "BackgroundFile": "memory lane bg better better.png",
    "MapId": "91685",
    "MapSetId": "20075",
    "Mode": "Keys4",
    "Title": "Memory Lane",
    "Artist": "AcesToAces",
    "Source": "''",
    "Tags": "yasuha, flyday chinatown, future funk, groove, sv",
    "Creator": "svKona",
    "DifficultyName": "Advanced",
    "Description": "Created at 1658317021000",
    "EditorLayers": "[]",
    "CustomAudioSamples": "[]",
    "SoundEffects": "[]",
    "BPM": 128,
    "SliderVelocities": "[]"
  },
  "20075 - 750/91713.qua": {
    "AudioFile": "audio.mp3",
    "SongPreviewTime": "14970",
    "BackgroundFile": "memory lane bg better better.png",
    "MapId": "91713",
    "MapSetId": "20075",
    "Mode": "Keys4",
    "Title": "Memory Lane",
    "Artist": "AcesToAces",
    "Source": "''",
    "Tags": "yasuha, flyday chinatown, future funk, groove, sv",
    "Creator": "svKona",
    "DifficultyName": "Easy",
    "Description": "Created at 1658343840000",
    "EditorLayers": "[]",
    "CustomAudioSamples": "[]",
    "SoundEffects": "[]",
    "BPM": 128,
    "SliderVelocities": "[]"
  },
  "20075 - 750/91714.qua": {
    "AudioFile": "audio.mp3",
    "SongPreviewTime": "14970",
    "BackgroundFile": "memory lane bg better better.png",
    "MapId": "91714",
    "MapSetId": "20075",
    "Mode": "Keys4",
    "Title": "Memory Lane",
    "Artist": "AcesToAces",
    "Source": "''",
    "Tags": "yasuha, flyday chinatown, future funk, groove, sv",
    "Creator": "svKona",
    "DifficultyName": "Beginner",
    "Description": "Created at 1658345311000",
    "EditorLayers": "[]",
    "CustomAudioSamples": "[]",
    "SoundEffects": "[]",
    "BPM": 128,
    "SliderVelocities": "[]"
  },
  "20075 - 750/91722.qua": {
    "AudioFile": "audio.mp3",
    "SongPreviewTime": "14970",
    "BackgroundFile": "memory lane bg better better.png",
    "MapId": "91722",
    "MapSetId": "20075",
    "Mode": "Keys4",
    "Title": "Memory Lane",
    "Artist": "AcesToAces",
    "Source": "''",
    "Tags": "yasuha, flyday chinatown, future funk, groove, sv",
    "Creator": "svKona",
    "DifficultyName": "Normal",
    "Description": "Created at 1658345796000",
    "EditorLayers": "[]",
    "CustomAudioSamples": "[]",
    "SoundEffects": "[]",
    "BPM": 128,
    "SliderVelocities": "[]"
  },
  "20075 - 750/91806.qua": {
    "AudioFile": "audio.mp3",
    "SongPreviewTime": "14970",
    "BackgroundFile": "memory lane bg better better.png",
    "MapId": "91806",
    "MapSetId": "20075",
    "Mode": "Keys4",
    "Title": "Memory Lane",
    "Artist": "AcesToAces",
    "Source": "''",
    "Tags": "yasuha, flyday chinatown, future funk, groove, sv",
    "Creator": "svKona",
    "DifficultyName": "Novice",
    "Description": "Created at 1658422238000",
    "EditorLayers": "[]",
    "CustomAudioSamples": "[]",
    "SoundEffects": "[]",
    "BPM": 128,
    "SliderVelocities": "[]"
  },
  "HyuN - CrossOver/1159.qua": {
    "AudioFile": "audio.mp3",
    "SongPreviewTime": "48206",
    "BackgroundFile": "CrossOverBGR.jpg",
    "MapId": "1159",
    "MapSetId": "523",
    "Mode": "Keys4",
    "Title": "CrossOver",
    "Artist": "HyuN feat. LyuU",
    "Source": "PUMP IT UP PRIME 2",
    "Tags": "Digital Stepcore",
    "Creator": "foxibun",
    "DifficultyName": "Beginner",
    "Description": "''",
    "EditorLayers": "[]",
    "BPM": 200,
    "SliderVelocities": "[]"
  },
  "HyuN - CrossOver/1160.qua": {
    "AudioFile": "audio.mp3",
    "SongPreviewTime": "48206",
    "BackgroundFile": "CrossOverEZ.jpg",
    "MapId": "1160",
    "MapSetId": "523",
    "Mode": "Keys4",
    "Title": "CrossOver",
    "Artist": "HyuN feat. LyuU",
    "Source": "PUMP IT UP PRIME 2",
    "Tags": "Digital Stepcore",
    "Creator": "foxibun",
    "DifficultyName": "Easy",
    "Description": "''",
    "EditorLayers": "[]",
    "BPM": 200,
    "SliderVelocities": "[]"
  },
  "HyuN - CrossOver/1161.qua": {
    "AudioFile": "audio.mp3",
    "SongPreviewTime": "48206",
    "BackgroundFile": "CrossOverNM.jpg",
    "MapId": "1161",
    "MapSetId": "523",
    "Mode": "Keys4",
    "Title": "CrossOver",
    "Artist": "HyuN feat. LyuU",
    "Source": "PUMP IT UP PRIME 2",
    "Tags": "Digital Stepcore",
    "Creator": "foxibun",
    "DifficultyName": "Normal",
    "Description": "''",
    "EditorLayers": "[]",
    "BPM": 200,
    "SliderVelocities": "[]"
  },
  "HyuN - CrossOver/1162.qua": {
    "AudioFile": "audio.mp3",
    "SongPreviewTime": "48206",
    "BackgroundFile": "CrossOverHD.jpg",
    "MapId": "1162",
    "MapSetId": "523",
    "Mode": "Keys4",
    "Title": "CrossOver",
    "Artist": "HyuN feat. LyuU",
    "Source": "PUMP IT UP PRIME 2",
    "Tags": "Digital Stepcore",
    "Creator": "foxibun",
    "DifficultyName": "Hard",
    "Description": "''",
    "EditorLayers": "[]",
    "BPM": 200,
    "SliderVelocities": "[]"
  },
  "HyuN - CrossOver/1164.qua": {
    "AudioFile": "audio.mp3",
    "SongPreviewTime": "48206",
    "BackgroundFile": "CrossOverEX.jpg",
    "MapId": "1164",
    "MapSetId": "523",
    "Mode": "Keys4",
    "Title": "CrossOver",
    "Artist": "HyuN feat. LyuU",
    "Source": "PUMP IT UP PRIME 2",
    "Tags": "Digital Stepcore",
    "Creator": "foxibun",
    "DifficultyName": "Revelation",
    "Description": "''",
    "EditorLayers": "[]",
    "BPM": 200,
    "SliderVelocities": "[]"
  },
  "HyuN - CrossOver/3615.qua": {
    "AudioFile": "audio.mp3",
    "SongPreviewTime": "48206",
    "BackgroundFile": "CrossOverIN.jpg",
    "MapId": "3615",
    "MapSetId": "523",
    "Mode": "Keys4",
    "Title": "CrossOver",
    "Artist": "HyuN feat. LyuU",
    "Source": "PUMP IT UP PRIME 2",
    "Tags": "Digital Stepcore",
    "Creator": "foxibun",
    "DifficultyName": "yahweh's Insane",
    "Description": "Created at 1571964313000",
    "EditorLayers": "[]",
    "BPM": 200,
    "SliderVelocities": "[]"
  },
  "HyuN - Princess Of Winter/2043.qua": {
    "AudioFile": "audio.mp3",
    "SongPreviewTime": "89466",
    "BackgroundFile": "Princess of Winter.png",
    "MapId": "2043",
    "MapSetId": "563",
    "Mode": "Keys4",
    "Title": "Princess of Winter",
    "Artist": "HyuN",
    "Source": "Quaver",
    "Tags": "J-core Electronic Instumental Quaver Featured Artist",
    "Creator": "PianoLuigi",
    "DifficultyName": "Expert",
    "Description": "This is a Quaver converted version of PianoLuigi's map.",
    "EditorLayers": "[]",
    "BPM": 1,
    "SliderVelocities": "[]"
  },
  "HyuN - Princess Of Winter/2044.qua": {
    "AudioFile": "audio.mp3",
    "SongPreviewTime": "89466",
    "BackgroundFile": "Princess of Winter.png",
    "MapId": "2044",
    "MapSetId": "563",
    "Mode": "Keys4",
    "Title": "Princess of Winter",
    "Artist": "HyuN",
    "Source": "Quaver",
    "Tags": "J-core Electronic Instumental Quaver Featured Artist",
    "Creator": "PianoLuigi",
    "DifficultyName": "Advanced",
    "Description": "This is a Quaver converted version of PianoLuigi's map.",
    "EditorLayers": "[]",
    "BPM": 1,
    "SliderVelocities": "[]"
  },
  "HyuN - Princess Of Winter/2045.qua": {
    "AudioFile": "audio.mp3",
    "SongPreviewTime": "89466",
    "BackgroundFile": "Princess of Winter.png",
    "MapId": "2045",
    "MapSetId": "563",
    "Mode": "Keys4",
    "Title": "Princess of Winter",
    "Artist": "HyuN",
    "Source": "Quaver",
    "Tags": "J-core Electronic Instumental Quaver Featured Artist",
    "Creator": "PianoLuigi",
    "DifficultyName": "Insane",
    "Description": "This is a Quaver converted version of PianoLuigi's map.",
    "EditorLayers": "[]",
    "BPM": 1,
    "SliderVelocities": "[]"
  },
  "HyuN - Princess Of Winter/2070.qua": {
    "AudioFile": "audio.mp3",
    "SongPreviewTime": "89466",
    "BackgroundFile": "Princess of Winter.png",
    "MapId": "2070",
    "MapSetId": "563",
    "Mode": "Keys4",
    "Title": "Princess of Winter",
    "Artist": "HyuN",
    "Source": "Quaver",
    "Tags": "J-core Electronic Instumental Quaver Featured Artist",
    "Creator": "PianoLuigi",
    "DifficultyName": "Normal",
    "Description": "Created at 1566504020000",
    "EditorLayers": "[]",
    "BPM": 1,
    "SliderVelocities": "[]"
  },
  "HyuN - Princess Of Winter/2071.qua": {
    "AudioFile": "audio.mp3",
    "SongPreviewTime": "89466",
    "BackgroundFile": "Princess of Winter.png",
    "MapId": "2071",
    "MapSetId": "563",
    "Mode": "Keys4",
    "Title": "Princess of Winter",
    "Artist": "HyuN",
    "Source": "Quaver",
    "Tags": "J-core Electronic Instumental Quaver Featured Artist",
    "Creator": "PianoLuigi",
    "DifficultyName": "Easy",
    "Description": "Created at 1566505218000",
    "EditorLayers": "[]",
    "BPM": 1,
    "SliderVelocities": "[]"
  },
  "HyuN - Princess Of Winter/2072.qua": {
    "AudioFile": "audio.mp3",
    "SongPreviewTime": "89466",
    "BackgroundFile": "Princess of Winter.png",
    "MapId": "2072",
    "MapSetId": "563",
    "Mode": "Keys4",
    "Title": "Princess of Winter",
    "Artist": "HyuN",
    "Source": "Quaver",
    "Tags": "J-core Electronic Instumental Quaver Featured Artist",
    "Creator": "PianoLuigi",
    "DifficultyName": "Beginner",
    "Description": "Created at 1566505630000",
    "EditorLayers": "[]",
    "BPM": 1,
    "SliderVelocities": "[]"
  },
  "HyuN - Princess Of Winter/3940.qua": {
    "AudioFile": "audio.mp3",
    "SongPreviewTime": "89466",
    "BackgroundFile": "Princess of Winter.png",
    "MapId": "3940",
    "MapSetId": "563",
    "Mode": "Keys4",
    "Title": "Princess of Winter",
    "Artist": "HyuN",
    "Source": "Quaver",
    "Tags": "J-core Electronic Instumental Quaver Featured Artist",
    "Creator": "PianoLuigi",
    "DifficultyName": "Hard",
    "Description": "Created at 1570613666000",
    "EditorLayers": "[]",
    "BPM": 1,
    "SliderVelocities": "[]"
  },
  "HyuN - Princess Of Winter/5507.qua": {
    "AudioFile": "audio.mp3",
    "SongPreviewTime": "89466",
    "BackgroundFile": "Princess of Winter.png",
    "MapId": "5507",
    "MapSetId": "563",
    "Mode": "Keys4",
    "Title": "Princess of Winter",
    "Artist": "HyuN",
    "Source": "Quaver",
    "Tags": "J-core Electronic Instumental Quaver Featured Artist",
    "Creator": "PianoLuigi",
    "DifficultyName": "Novice",
    "Description": "Created at 1576367012000",
    "EditorLayers": "[]",
    "BPM": 1,
    "SliderVelocities": "[]"
  },
  "HyuN feat. Yuri - Disorder/12278.qua": {
    "AudioFile": "HyuN - Disorder (feat. YURI).mp3",
    "SongPreviewTime": "11749",
    "BackgroundFile": "bg.png",
    "MapId": "12278",
    "MapSetId": "994",
    "Mode": "Keys4",
    "Title": "Disorder",
    "Artist": "HyuN feat. Yuri",
    "Source": "Quaver",
    "Tags": "Artcore J-core Instrumental Quaver Featured Artist",
    "Creator": "PianoLuigi",
    "DifficultyName": "Expert",
    "Description": "Created at 1573305358000",
    "EditorLayers": "[]",
    "CustomAudioSamples": "[]",
    "SoundEffects": "[]",
    "BPM": 193,
    "SliderVelocities": ""
  },
  "HyuN feat. Yuri - Disorder/12287.qua": {
    "AudioFile": "HyuN - Disorder (feat. YURI).mp3",
    "SongPreviewTime": "11749",
    "BackgroundFile": "bg.png",
    "MapId": "12287",
    "MapSetId": "994",
    "Mode": "Keys4",
    "Title": "Disorder",
    "Artist": "HyuN feat. Yuri",
    "Source": "Quaver",
    "Tags": "Artcore J-core Instrumental Quaver Featured Artist",
    "Creator": "PianoLuigi",
    "DifficultyName": "Insane",
    "Description": "Created at 1591298040000",
    "EditorLayers": "[]",
    "CustomAudioSamples": "[]",
    "SoundEffects": "[]",
    "BPM": 193,
    "SliderVelocities": "[]"
  },
  "HyuN feat. Yuri - Disorder/12288.qua": {
    "AudioFile": "HyuN - Disorder (feat. YURI).mp3",
    "SongPreviewTime": "11749",
    "BackgroundFile": "bg.png",
    "MapId": "12288",
    "MapSetId": "994",
    "Mode": "Keys4",
    "Title": "Disorder",
    "Artist": "HyuN feat. Yuri",
    "Source": "Quaver",
    "Tags": "Artcore J-core Instrumental Quaver Featured Artist",
    "Creator": "PianoLuigi",
    "DifficultyName": "Normal",
    "Description": "Created at 1591301890000",
    "EditorLayers": "[]",
    "CustomAudioSamples": "[]",
    "SoundEffects": "[]",
    "BPM": 193,
    "SliderVelocities": "[]"
  },
  "HyuN feat. Yuri - Disorder/12289.qua": {
    "AudioFile": "HyuN - Disorder (feat. YURI).mp3",
    "SongPreviewTime": "11749",
    "BackgroundFile": "bg.png",
    "MapId": "12289",
    "MapSetId": "994",
    "Mode": "Keys4",
    "Title": "Disorder",
    "Artist": "HyuN feat. Yuri",
    "Source": "Quaver",
    "Tags": "Artcore J-core Instrumental Quaver Featured Artist",
    "Creator": "PianoLuigi",
    "DifficultyName": "Easy",
    "Description": "Created at 1591303119000",
    "EditorLayers": "[]",
    "CustomAudioSamples": "[]",
    "SoundEffects": "[]",
    "BPM": 193,
    "SliderVelocities": "[]"
  },
  "HyuN feat. Yuri - Disorder/12290.qua": {
    "AudioFile": "HyuN - Disorder (feat. YURI).mp3",
    "SongPreviewTime": "11749",
    "BackgroundFile": "bg.png",
    "MapId": "12290",
    "MapSetId": "994",
    "Mode": "Keys4",
    "Title": "Disorder",
    "Artist": "HyuN feat. Yuri",
    "Source": "Quaver",
    "Tags": "Artcore J-core Instrumental Quaver Featured Artist",
    "Creator": "PianoLuigi",
    "DifficultyName": "Beginner",
    "Description": "Created at 1591304350000",
    "EditorLayers": "[]",
    "CustomAudioSamples": "[]",
    "SoundEffects": "[]",
    "BPM": 193,
    "SliderVelocities": "[]"
  },
  "HyuN feat. Yuri - Disorder/12328.qua": {
    "AudioFile": "HyuN - Disorder (feat. YURI).mp3",
    "SongPreviewTime": "11749",
    "BackgroundFile": "bg.png",
    "MapId": "12328",
    "MapSetId": "994",
    "Mode": "Keys4",
    "Title": "Disorder",
    "Artist": "HyuN feat. Yuri",
    "Source": "Quaver",
    "Tags": "Artcore J-core Instrumental Quaver Featured Artist",
    "Creator": "PianoLuigi",
    "DifficultyName": "Milky's Hard",
    "Description": "Created at 1591384358000",
    "EditorLayers": "[]",
    "CustomAudioSamples": "[]",
    "SoundEffects": "[]",
    "BPM": 193,
    "SliderVelocities": "[]"
  },
  "HyuN feat. Yuri - Disorder/12329.qua": {
    "AudioFile": "HyuN - Disorder (feat. YURI).mp3",
    "SongPreviewTime": "11749",
    "BackgroundFile": "bg.png",
    "MapId": "12329",
    "MapSetId": "994",
    "Mode": "Keys4",
    "Title": "Disorder",
    "Artist": "HyuN feat. Yuri",
    "Source": "Quaver",
    "Tags": "Artcore J-core Instrumental Quaver Featured Artist",
    "Creator": "PianoLuigi",
    "DifficultyName": "Milky's Hyper",
    "Description": "Created at 1591314860000",
    "EditorLayers": "[]",
    "CustomAudioSamples": "[]",
    "SoundEffects": "[]",
    "BPM": 193,
    "SliderVelocities": "[]"
  },
  "Lollipop - vibing oustide the supermarket at 1am/11507.qua": {
    "AudioFile": "why_are_there_frozen_pizzas_in_the_detergent_aisle.mp3",
    "SongPreviewTime": "24586",
    "BackgroundFile": "bg (1).jpg",
    "MapId": "11507",
    "MapSetId": "954",
    "Mode": "Keys7",
    "Title": "vibing oustide the supermarket at 1am",
    "Artist": "Lollipop",
    "Source": "''",
    "Tags": "lofi",
    "Creator": "yahweh",
    "DifficultyName": "late night vibes",
    "Description": "Created at 1589749952000",
    "EditorLayers": "[]",
    "CustomAudioSamples": "[]",
    "SoundEffects": "[]",
    "BPM": 78,
    "SliderVelocities": "[]"
  },
  "Lollipop - vibing oustide the supermarket at 1am/11508.qua": {
    "AudioFile": "why_are_there_frozen_pizzas_in_the_detergent_aisle.mp3",
    "SongPreviewTime": "24586",
    "BackgroundFile": "bg (1).jpg",
    "MapId": "11508",
    "MapSetId": "954",
    "Mode": "Keys7",
    "Title": "vibing oustide the supermarket at 1am",
    "Artist": "Lollipop",
    "Source": "''",
    "Tags": "lofi",
    "Creator": "yahweh",
    "DifficultyName": "Beginner",
    "Description": "Created at 1589818689000",
    "EditorLayers": "[]",
    "CustomAudioSamples": "[]",
    "SoundEffects": "[]",
    "BPM": 78,
    "SliderVelocities": "[]"
  },
  "Lollipop - vibing oustide the supermarket at 1am/11509.qua": {
    "AudioFile": "why_are_there_frozen_pizzas_in_the_detergent_aisle.mp3",
    "SongPreviewTime": "24586",
    "BackgroundFile": "bg (1).jpg",
    "MapId": "11509",
    "MapSetId": "954",
    "Mode": "Keys7",
    "Title": "vibing oustide the supermarket at 1am",
    "Artist": "Lollipop",
    "Source": "''",
    "Tags": "lofi",
    "Creator": "yahweh",
    "DifficultyName": "Easy",
    "Description": "Created at 1589819019000",
    "EditorLayers": "[]",
    "CustomAudioSamples": "[]",
    "SoundEffects": "[]",
    "BPM": 78,
    "SliderVelocities": "[]"
  },
  "Lollipop - vibing oustide the supermarket at 1am/11510.qua": {
    "AudioFile": "why_are_there_frozen_pizzas_in_the_detergent_aisle.mp3",
    "SongPreviewTime": "24586",
    "BackgroundFile": "bg (1).jpg",
    "MapId": "11510",
    "MapSetId": "954",
    "Mode": "Keys7",
    "Title": "vibing oustide the supermarket at 1am",
    "Artist": "Lollipop",
    "Source": "''",
    "Tags": "lofi",
    "Creator": "yahweh",
    "DifficultyName": "Normal",
    "Description": "Created at 1589819425000",
    "EditorLayers": "[]",
    "CustomAudioSamples": "[]",
    "SoundEffects": "[]",
    "BPM": 78,
    "SliderVelocities": "[]"
  },
  "Plum - Fantasy Collision/10930.qua": {
    "AudioFile": "audio.mp3",
    "SongPreviewTime": "98600",
    "BackgroundFile": "spacething.png",
    "MapId": "10930",
    "MapSetId": "923",
    "Mode": "Keys4",
    "Title": "Fantasy Collision",
    "Artist": "Plum",
    "Source": "Quaver",
    "Tags": "' \ud658\uc0c1\ucda9\ub3cc Quaver Featured Artist Electronic Instrumental Artcore'",
    "Creator": "PianoLuigi",
    "DifficultyName": "Hard",
    "Description": "Created at 1588790326000",
    "EditorLayers": "[]",
    "CustomAudioSamples": "[]",
    "SoundEffects": "[]",
    "BPM": 180,
    "SliderVelocities": "[]"
  },
  "Plum - Fantasy Collision/10931.qua": {
    "AudioFile": "audio.mp3",
    "SongPreviewTime": "98600",
    "BackgroundFile": "spacething.png",
    "MapId": "10931",
    "MapSetId": "923",
    "Mode": "Keys4",
    "Title": "Fantasy Collision",
    "Artist": "Plum",
    "Source": "Quaver",
    "Tags": "' \ud658\uc0c1\ucda9\ub3cc Quaver Featured Artist Electronic Instrumental Artcore'",
    "Creator": "PianoLuigi",
    "DifficultyName": "Easy",
    "Description": "Created at 1588792821000",
    "EditorLayers": "[]",
    "CustomAudioSamples": "[]",
    "SoundEffects": "[]",
    "BPM": 180,
    "SliderVelocities": "[]"
  },
  "Plum - Fantasy Collision/10932.qua": {
    "AudioFile": "audio.mp3",
    "SongPreviewTime": "98600",
    "BackgroundFile": "spacething.png",
    "MapId": "10932",
    "MapSetId": "923",
    "Mode": "Keys4",
    "Title": "Fantasy Collision",
    "Artist": "Plum",
    "Source": "Quaver",
    "Tags": "' \ud658\uc0c1\ucda9\ub3cc Quaver Featured Artist Electronic Instrumental Artcore'",
    "Creator": "PianoLuigi",
    "DifficultyName": "Beginner",
    "Description": "Created at 1588793763000",
    "EditorLayers": "[]",
    "CustomAudioSamples": "[]",
    "SoundEffects": "[]",
    "BPM": 180,
    "SliderVelocities": "[]"
  },
  "Plum - Fantasy Collision/10933.qua": {
    "AudioFile": "audio.mp3",
    "SongPreviewTime": "98600",
    "BackgroundFile": "spacething.png",
    "MapId": "10933",
    "MapSetId": "923",
    "Mode": "Keys4",
    "Title": "Fantasy Collision",
    "Artist": "Plum",
    "Source": "Quaver",
    "Tags": "' \ud658\uc0c1\ucda9\ub3cc Quaver Featured Artist Electronic Instrumental Artcore'",
    "Creator": "PianoLuigi",
    "DifficultyName": "Normal",
    "Description": "Created at 1588451540000",
    "EditorLayers": "[]",
    "CustomAudioSamples": "[]",
    "SoundEffects": "[]",
    "BPM": 180,
    "SliderVelocities": "[]"
  },
  "Rabbit House - Have A Party Time!/12.qua": {
    "AudioFile": "audio.mp3",
    "SongPreviewTime": "93073",
    "BackgroundFile": "bg.jpg",
    "MapId": "12",
    "MapSetId": "9",
    "Mode": "Keys7",
    "Title": "Have A Party Time!",
    "Artist": "Rabbit House",
    "Source": "''",
    "Tags": "''",
    "Creator": "Quaver",
    "DifficultyName": "anti-'s 7K Party",
    "Description": "''",
    "BPM": 205,
    "SliderVelocities": ""
  },
  "Rabbit House - Have A Party Time!/13.qua": {
    "AudioFile": "audio.mp3",
    "SongPreviewTime": "93670",
    "BackgroundFile": "bg.jpg",
    "MapId": "13",
    "MapSetId": "9",
    "Mode": "Keys4",
    "Title": "Have A Party Time!",
    "Artist": "Rabbit House",
    "Source": "''",
    "Tags": "''",
    "Creator": "Quaver",
    "DifficultyName": "neyoru's 4K Easy",
    "Description": "''",
    "BPM": 205,
    "SliderVelocities": ""
  },
  "Rabbit House - Have A Party Time!/14.qua": {
    "AudioFile": "audio.mp3",
    "SongPreviewTime": "93670",
    "BackgroundFile": "bg.jpg",
    "MapId": "14",
    "MapSetId": "9",
    "Mode": "Keys4",
    "Title": "Have A Party Time!",
    "Artist": "Rabbit House",
    "Source": "''",
    "Tags": "''",
    "Creator": "Quaver",
    "DifficultyName": "neyoru's 4K Expert",
    "Description": "''",
    "BPM": 205,
    "SliderVelocities": ""
  },
  "Rabbit House - Have A Party Time!/15.qua": {
    "AudioFile": "audio.mp3",
    "SongPreviewTime": "93670",
    "BackgroundFile": "bg.jpg",
    "MapId": "15",
    "MapSetId": "9",
    "Mode": "Keys4",
    "Title": "Have A Party Time!",
    "Artist": "Rabbit House",
    "Source": "''",
    "Tags": "''",
    "Creator": "Quaver",
    "DifficultyName": "neyoru's 4K Hard",
    "Description": "''",
    "BPM": 205,
    "SliderVelocities": ""
  },
  "Rabbit House - Have A Party Time!/16.qua": {
    "AudioFile": "audio.mp3",
    "SongPreviewTime": "93670",
    "BackgroundFile": "bg.jpg",
    "MapId": "16",
    "MapSetId": "9",
    "Mode": "Keys4",
    "Title": "Have A Party Time!",
    "Artist": "Rabbit House",
    "Source": "''",
    "Tags": "''",
    "Creator": "Quaver",
    "DifficultyName": "neyoru's 4K Insane",
    "Description": "''",
    "BPM": 205,
    "SliderVelocities": ""
  },
  "Rabbit House - Have A Party Time!/17.qua": {
    "AudioFile": "audio.mp3",
    "SongPreviewTime": "93670",
    "BackgroundFile": "bg.jpg",
    "MapId": "17",
    "MapSetId": "9",
    "Mode": "Keys4",
    "Title": "Have A Party Time!",
    "Artist": "Rabbit House",
    "Source": "''",
    "Tags": "''",
    "Creator": "Quaver",
    "DifficultyName": "neyoru's 4K Normal",
    "Description": "''",
    "BPM": 205,
    "SliderVelocities": ""
  },
  "zetoban - Csikos Post/1413.qua": {
    "AudioFile": "zetoban - Csikos Post.mp3",
    "SongPreviewTime": "77756",
    "BackgroundFile": "csikos post bg.png",
    "MapId": "1413",
    "MapSetId": "536",
    "Mode": "Keys4",
    "Title": "Csikos Post",
    "Artist": "zetoban",
    "Source": "''",
    "Tags": "J-Core Eurobeat Hermann Necke Quaver Featured Artist",
    "Creator": "PianoLuigi",
    "DifficultyName": "Insane",
    "Description": "Created at 1564247436000",
    "EditorLayers": "[]",
    "BPM": 185,
    "SliderVelocities": "[]"
  },
  "zetoban - Csikos Post/1414.qua": {
    "AudioFile": "zetoban - Csikos Post.mp3",
    "SongPreviewTime": "77756",
    "BackgroundFile": "csikos post bg.png",
    "MapId": "1414",
    "MapSetId": "536",
    "Mode": "Keys4",
    "Title": "Csikos Post",
    "Artist": "zetoban",
    "Source": "''",
    "Tags": "J-Core Eurobeat Hermann Necke Quaver Featured Artist",
    "Creator": "PianoLuigi",
    "DifficultyName": "Expert",
    "Description": "''",
    "EditorLayers": "[]",
    "BPM": 185,
    "SliderVelocities": "[]"
  },
  "zetoban - Csikos Post/1415.qua": {
    "AudioFile": "zetoban - Csikos Post.mp3",
    "SongPreviewTime": "77756",
    "BackgroundFile": "csikos post bg.png",
    "MapId": "1415",
    "MapSetId": "536",
    "Mode": "Keys4",
    "Title": "Csikos Post",
    "Artist": "zetoban",
    "Source": "''",
    "Tags": "J-Core Eurobeat Hermann Necke Quaver Featured Artist",
    "Creator": "PianoLuigi",
    "DifficultyName": "Easy",
    "Description": "Created at 1564412664000",
    "EditorLayers": "[]",
    "BPM": 185,
    "SliderVelocities": "[]"
  },
  "zetoban - Csikos Post/1416.qua": {
    "AudioFile": "zetoban - Csikos Post.mp3",
    "SongPreviewTime": "77756",
    "BackgroundFile": "csikos post bg.png",
    "MapId": "1416",
    "MapSetId": "536",
    "Mode": "Keys4",
    "Title": "Csikos Post",
    "Artist": "zetoban",
    "Source": "''",
    "Tags": "J-Core Eurobeat Hermann Necke Quaver Featured Artist",
    "Creator": "PianoLuigi",
    "DifficultyName": "Beginner",
    "Description": "Created at 1564413331000",
    "EditorLayers": "[]",
    "BPM": 185,
    "SliderVelocities": "[]"
  },
  "zetoban - Csikos Post/1417.qua": {
    "AudioFile": "zetoban - Csikos Post.mp3",
    "SongPreviewTime": "77756",
    "BackgroundFile": "csikos post bg.png",
    "MapId": "1417",
    "MapSetId": "536",
    "Mode": "Keys4",
    "Title": "Csikos Post",
    "Artist": "zetoban",
    "Source": "''",
    "Tags": "J-Core Eurobeat Hermann Necke Quaver Featured Artist",
    "Creator": "PianoLuigi",
    "DifficultyName": "Hard",
    "Description": "Created at 1564594597000",
    "EditorLayers": "[]",
    "BPM": 185,
    "SliderVelocities": "[]"
  },
  "zetoban - Csikos Post/1418.qua": {
    "AudioFile": "zetoban - Csikos Post.mp3",
    "SongPreviewTime": "77756",
    "BackgroundFile": "csikos post bg.png",
    "MapId": "1418",
    "MapSetId": "536",
    "Mode": "Keys4",
    "Title": "Csikos Post",
    "Artist": "zetoban",
    "Source": "''",
    "Tags": "J-Core Eurobeat Hermann Necke Quaver Featured Artist",
    "Creator": "PianoLuigi",
    "DifficultyName": "Normal",
    "Description": "Created at 1564598955000",
    "EditorLayers": "[]",
    "BPM": 185,
    "SliderVelocities": "[]"
  },
  "zetoban - Flowering Night/10859.qua": {
    "AudioFile": "zetoban - Flowering Night (1).mp3",
    "SongPreviewTime": "78114",
    "BackgroundFile": "hmhm.jpg",
    "MapId": "10859",
    "MapSetId": "919",
    "Mode": "Keys4",
    "Title": "Flowering Night",
    "Artist": "zetoban",
    "Source": "Quaver",
    "Tags": "Touhou ZUN Phantasmagoria of Flower View PoFV Sakuya's Theme Night of Nights Electronic Instrumental J-core Eurobeat Quaver Featured Artist",
    "Creator": "PianoLuigi",
    "DifficultyName": "Insane",
    "Description": "Created at 1568037830000",
    "EditorLayers": "[]",
    "CustomAudioSamples": "[]",
    "SoundEffects": "[]",
    "BPM": 175,
    "SliderVelocities": "[]"
  },
  "zetoban - Flowering Night/10860.qua": {
    "AudioFile": "zetoban - Flowering Night (1).mp3",
    "SongPreviewTime": "78114",
    "BackgroundFile": "hmhm.jpg",
    "MapId": "10860",
    "MapSetId": "919",
    "Mode": "Keys4",
    "Title": "Flowering Night",
    "Artist": "zetoban",
    "Source": "Quaver",
    "Tags": "Touhou ZUN Phantasmagoria of Flower View PoFV Sakuya's Theme Night of Nights Electronic Instrumental J-core Eurobeat Quaver Featured Artist",
    "Creator": "PianoLuigi",
    "DifficultyName": "Advanced",
    "Description": "Created at 1588458255000",
    "EditorLayers": "[]",
    "CustomAudioSamples": "[]",
    "SoundEffects": "[]",
    "BPM": 175,
    "SliderVelocities": "[]"
  },
  "zetoban - Flowering Night/10861.qua": {
    "AudioFile": "zetoban - Flowering Night (1).mp3",
    "SongPreviewTime": "78114",
    "BackgroundFile": "hmhm.jpg",
    "MapId": "10861",
    "MapSetId": "919",
    "Mode": "Keys4",
    "Title": "Flowering Night",
    "Artist": "zetoban",
    "Source": "Quaver",
    "Tags": "Touhou ZUN Phantasmagoria of Flower View PoFV Sakuya's Theme Night of Nights Electronic Instrumental J-core Eurobeat Quaver Featured Artist",
    "Creator": "PianoLuigi",
    "DifficultyName": "Hard",
    "Description": "Created at 1588501906000",
    "EditorLayers": "[]",
    "CustomAudioSamples": "[]",
    "SoundEffects": "[]",
    "BPM": 175,
    "SliderVelocities": "[]"
  },
  "zetoban - Flowering Night/10862.qua": {
    "AudioFile": "zetoban - Flowering Night (1).mp3",
    "SongPreviewTime": "78114",
    "BackgroundFile": "hmhm.jpg",
    "MapId": "10862",
    "MapSetId": "919",
    "Mode": "Keys4",
    "Title": "Flowering Night",
    "Artist": "zetoban",
    "Source": "Quaver",
    "Tags": "Touhou ZUN Phantasmagoria of Flower View PoFV Sakuya's Theme Night of Nights Electronic Instrumental J-core Eurobeat Quaver Featured Artist",
    "Creator": "PianoLuigi",
    "DifficultyName": "Normal",
    "Description": "Created at 1588519991000",
    "EditorLayers": "[]",
    "CustomAudioSamples": "[]",
    "SoundEffects": "[]",
    "BPM": 175,
    "SliderVelocities": "[]"
  },
  "zetoban - Flowering Night/10863.qua": {
    "AudioFile": "zetoban - Flowering Night (1).mp3",
    "SongPreviewTime": "78114",
    "BackgroundFile": "hmhm.jpg",
    "MapId": "10863",
    "MapSetId": "919",
    "Mode": "Keys4",
    "Title": "Flowering Night",
    "Artist": "zetoban",
    "Source": "Quaver",
    "Tags": "Touhou ZUN Phantasmagoria of Flower View PoFV Sakuya's Theme Night of Nights Electronic Instrumental J-core Eurobeat Quaver Featured Artist",
    "Creator": "PianoLuigi",
    "DifficultyName": "Easy",
    "Description": "Created at 1588520028000",
    "EditorLayers": "[]",
    "CustomAudioSamples": "[]",
    "SoundEffects": "[]",
    "BPM": 175,
    "SliderVelocities": "[]"
  },
  "zetoban - Flowering Night/10864.qua": {
    "AudioFile": "zetoban - Flowering Night (1).mp3",
    "SongPreviewTime": "78114",
    "BackgroundFile": "hmhm.jpg",
    "MapId": "10864",
    "MapSetId": "919",
    "Mode": "Keys4",
    "Title": "Flowering Night",
    "Artist": "zetoban",
    "Source": "Quaver",
    "Tags": "Touhou ZUN Phantasmagoria of Flower View PoFV Sakuya's Theme Night of Nights Electronic Instrumental J-core Eurobeat Quaver Featured Artist",
    "Creator": "PianoLuigi",
    "DifficultyName": "Beginner",
    "Description": "Created at 1588520036000",
    "EditorLayers": "[]",
    "CustomAudioSamples": "[]",
    "SoundEffects": "[]",
    "BPM": 175,
    "SliderVelocities": "[]"
  },
  "zetoban - Umami Packed Mountaineering/9111.qua": {
    "AudioFile": "audio.mp3",
    "SongPreviewTime": "-1",
    "BackgroundFile": "zetoban bg (1).jpg",
    "MapId": "9111",
    "MapSetId": "822",
    "Mode": "Keys7",
    "Title": "Umami Packed Mountaineering",
    "Artist": "zetoban",
    "Source": "''",
    "Tags": "Chiptune, Electronic, Quaver",
    "Creator": "yahweh",
    "DifficultyName": "Ascension",
    "Description": "This is a Quaver converted version of yahweh's map.",
    "EditorLayers": "[]",
    "CustomAudioSamples": "[]",
    "SoundEffects": "[]",
    "BPM": 155,
    "SliderVelocities": "[]"
  },
  "zetoban - Umami Packed Mountaineering/9112.qua": {
    "AudioFile": "audio.mp3",
    "SongPreviewTime": "-1",
    "BackgroundFile": "zetoban bg (1).jpg",
    "MapId": "9112",
    "MapSetId": "822",
    "Mode": "Keys7",
    "Title": "Umami Packed Mountaineering",
    "Artist": "zetoban",
    "Source": "''",
    "Tags": "Chiptune, Electronic, Quaver",
    "Creator": "yahweh",
    "DifficultyName": "Beginner",
    "Description": "This is a Quaver converted version of yahweh's map.",
    "EditorLayers": "[]",
    "CustomAudioSamples": "[]",
    "SoundEffects": "[]",
    "BPM": 155,
    "SliderVelocities": "[]"
  },
  "zetoban - Umami Packed Mountaineering/9113.qua": {
    "AudioFile": "audio.mp3",
    "SongPreviewTime": "-1",
    "BackgroundFile": "zetoban bg (1).jpg",
    "MapId": "9113",
    "MapSetId": "822",
    "Mode": "Keys7",
    "Title": "Umami Packed Mountaineering",
    "Artist": "zetoban",
    "Source": "''",
    "Tags": "Chiptune, Electronic, Quaver",
    "Creator": "yahweh",
    "DifficultyName": "Easy",
    "Description": "This is a Quaver converted version of yahweh's map.",
    "EditorLayers": "[]",
    "CustomAudioSamples": "[]",
    "SoundEffects": "[]",
    "BPM": 155,
    "SliderVelocities": "[]"
  },
  "zetoban - Umami Packed Mountaineering/9114.qua": {
    "AudioFile": "audio.mp3",
    "SongPreviewTime": "-1",
    "BackgroundFile": "zetoban bg (1).jpg",
    "MapId": "9114",
    "MapSetId": "822",
    "Mode": "Keys7",
    "Title": "Umami Packed Mountaineering",
    "Artist": "zetoban",
    "Source": "''",
    "Tags": "Chiptune, Electronic, Quaver",
    "Creator": "yahweh",
    "DifficultyName": "Hard",
    "Description": "This is a Quaver converted version of yahweh's map.",
    "EditorLayers": "[]",
    "CustomAudioSamples": "[]",
    "SoundEffects": "[]",
    "BPM": 155,
    "SliderVelocities": "[]"
  },
  "zetoban - Umami Packed Mountaineering/9115.qua": {
    "AudioFile": "audio.mp3",
    "SongPreviewTime": "-1",
    "BackgroundFile": "zetoban bg (1).jpg",
    "MapId": "9115",
    "MapSetId": "822",
    "Mode": "Keys7",
    "Title": "Umami Packed Mountaineering",
    "Artist": "zetoban",
    "Source": "''",
    "Tags": "Chiptune, Electronic, Quaver",
    "Creator": "yahweh",
    "DifficultyName": "Hydria's Advanced",
    "Description": "This is a Quaver converted version of yahweh's map.",
    "EditorLayers": "[]",
    "CustomAudioSamples": "[]",
    "SoundEffects": "[]",
    "BPM": 155,
    "SliderVelocities": "[]"
  },
  "zetoban - Umami Packed Mountaineering/9116.qua": {
    "AudioFile": "audio.mp3",
    "SongPreviewTime": "-1",
    "BackgroundFile": "zetoban bg (1).jpg",
    "MapId": "9116",
    "MapSetId": "822",
    "Mode": "Keys7",
    "Title": "Umami Packed Mountaineering",
    "Artist": "zetoban",
    "Source": "''",
    "Tags": "Chiptune, Electronic, Quaver",
    "Creator": "yahweh",
    "DifficultyName": "Insane",
    "Description": "This is a Quaver converted version of yahweh's map.",
    "EditorLayers": "[]",
    "CustomAudioSamples": "[]",
    "SoundEffects": "[]",
    "BPM": 155,
    "SliderVelocities": "[]"
  },
  "zetoban - Umami Packed Mountaineering/9117.qua": {
    "AudioFile": "audio.mp3",
    "SongPreviewTime": "-1",
    "BackgroundFile": "zetoban bg (1).jpg",
    "MapId": "9117",
    "MapSetId": "822",
    "Mode": "Keys7",
    "Title": "Umami Packed Mountaineering",
    "Artist": "zetoban",
    "Source": "''",
    "Tags": "Chiptune, Electronic, Quaver",
    "Creator": "yahweh",
    "DifficultyName": "Normal",
    "Description": "This is a Quaver converted version of yahweh's map.",
    "EditorLayers": "[]",
    "CustomAudioSamples": "[]",
    "SoundEffects": "[]",
    "BPM": 155,
    "SliderVelocities": "[]"
  },
  "zetoban - Umami Packed Mountaineering/9118.qua": {
    "AudioFile": "audio.mp3",
    "SongPreviewTime": "-1",
    "BackgroundFile": "zetoban bg (1).jpg",
    "MapId": "9118",
    "MapSetId": "822",
    "Mode": "Keys7",
    "Title": "Umami Packed Mountaineering",
    "Artist": "zetoban",
    "Source": "''",
    "Tags": "Chiptune, Electronic, Quaver",
    "Creator": "yahweh",
    "DifficultyName": "SUPEROMEGAHYPERBEGINNER",
    "Description": "This is a Quaver converted version of yahweh's map.",
    "EditorLayers": "[]",
    "CustomAudioSamples": "[]",
    "SoundEffects": "[]",
    "BPM": 155,
    "SliderVelocities": "[]"
  },
  "zetoban - Umami Packed Mountaineering/9119.qua": {
    "AudioFile": "audio.mp3",
    "SongPreviewTime": "-1",
    "BackgroundFile": "zetoban bg (1).jpg",
    "MapId": "9119",
    "MapSetId": "822",
    "Mode": "Keys7",
    "Title": "Umami Packed Mountaineering",
    "Artist": "zetoban",
    "Source": "''",
    "Tags": "Chiptune, Electronic, Quaver",
    "Creator": "yahweh",
    "DifficultyName": "Summit",
    "Description": "This is a Quaver converted version of yahweh's map.",
    "EditorLayers": "[]",
    "CustomAudioSamples": "[]",
    "SoundEffects": "[]",
    "BPM": 155,
    "SliderVelocities": "[]"
  }
}